PhysicsOneA/Collision.py
PhysicsOneA/EnergyConservation.py
PhysicsOneA/Forces.py
PhysicsOneA/Kinematics1D.py
PhysicsOneA/Kinematics2D.py
PhysicsOneA/NumericalMethods.py
PhysicsOneA/Rotation.py
PhysicsOneA/WorkAndEnergy.py
PhysicsOneA/__init__.py
PhysicsOneA/dependencies.py
PhysicsOneA/helpers.py
physicsonea-0.2.0.dist-info/licenses/LICENSE
physicsonea-0.2.0.dist-info/METADATA
physicsonea-0.2.0.dist-info/WHEEL
physicsonea-0.2.0.dist-info/top_level.txt
physicsonea-0.2.0.dist-info/RECORD
