Metadata-Version: 2.4
Name: PhysicsOneA
Version: 0.2.0
Summary: A comprehensive physics utility package for analysis and visualization made for the Physics1 course at DTU
Author: slayervictor
Author-email: Raaaainbow <seba7204@gmail.com>
License: MIT
Project-URL: Homepage, https://github.com/slayervictor/PhysicsOneA
Project-URL: Repository, https://github.com/slayervictor/PhysicsOneA
Project-URL: Issues, https://github.com/slayervictor/PhysicsOneA/issues
Requires-Python: >=3.8
License-File: LICENSE
Requires-Dist: numpy
Requires-Dist: sympy
Requires-Dist: scipy
Requires-Dist: pandas
Requires-Dist: uncertainties
Requires-Dist: matplotlib
Dynamic: license-file
